{
  "issue_number": 58,
  "requester": "will-lamerton",
  "member": "will",
  "base_pack_kind": "collective",
  "base_pack_id": "pi-versus-nanocoder",
  "context": null,
  "mirrored_channels": [
    "linkedin",
    "x"
  ],
  "additional_channels": [
    "instagram"
  ],
  "agent_mode": "bundled",
  "generated_at": "2026-05-18T13:31:57.508Z",
  "model": "minimax-m2.7",
  "phases": [
    {
      "phase": "channels",
      "attempts": 1,
      "final_status": "passed",
      "failures": []
    }
  ]
}